BusProjectUW_KO/__init__.py
BusProjectUW_KO/plot_data_set_speed.py
BusProjectUW_KO/src/__init__.py
BusProjectUW_KO/src/analyse.py
BusProjectUW_KO/src/collect.py
BusProjectUW_KO/src/collect_busStops.py
BusProjectUW_KO/src/collect_current_positions.py
BusProjectUW_KO/src/collect_dictionary.py
BusProjectUW_KO/src/collect_public_transport_routes.py
BusProjectUW_KO/src/collect_schedule.py
BusProjectUW_KO/src/filter_data.py
BusProjectUW_KO/src/filter_positions.py
BusProjectUW_KO/src/plot_data_set_schedule.py
BusProjectUW_KO/src/plot_data_set_speed.py
BusProjectUW_KO/src/tools.py
BusProjectUW_KO/test/__init__.py
BusProjectUW_KO-0.0.2.dist-info/LICENCE
BusProjectUW_KO-0.0.2.dist-info/METADATA
BusProjectUW_KO-0.0.2.dist-info/WHEEL
BusProjectUW_KO-0.0.2.dist-info/top_level.txt
BusProjectUW_KO-0.0.2.dist-info/RECORD
