Metadata-Version: 2.1
Name: BusProjectUW_KO
Version: 0.0.2
Summary: A package for the University of Warsaw Python Course
Home-page: https://github.com/Ometek16/UW_Python_Course
Author: Kuba Ornatek
Author-email: kuba.ornatek@gmail.com
Classifier: Programming Language :: Python :: 3
Classifier: License :: OSI Approved :: MIT License
Classifier: Operating System :: OS Independent
Requires-Python: >=3.6
License-File: LICENCE
